[{"roomId":1955,"numberOfFloors":12,"roomNumber":2,"capacity":12,"operationRoomType":0,"roomType":0,"occupied":false,"scheduled":null,"resource":[{"idItem":260255,"name":"Stolice","quantity":10,"manufacturer":"Manojlo","isStatic":true,"roomId":1955},{"idItem":888657,"name":"Aspirin","quantity":1,"manufacturer":"Galenika","isStatic":false,"roomId":1955}]},{"roomId":1905,"numberOfFloors":2,"roomNumber":2,"capacity":5,"operationRoomType":0,"roomType":3,"occupied":false,"scheduled":null,"resource":[{"idItem":260255,"name":"Stolice","quantity":20,"manufacturer":"Manojlo","isStatic":true,"roomId":1905},{"idItem":888657,"name":"Aspirin","quantity":15,"manufacturer":"Galenika","isStatic":false,"roomId":1905}]}]